{"name":"Navodhtml5","tagline":"Chrome插件：NA新在线影院html5播放器","body":"NavodHTML5\r\n===============\r\n\r\nChrome插件：NA新在线影院 HTML5播放器 \r\n为推广和普及华软 HTML5 而努力\r\n\r\n\r\n安装\r\n==============\r\n1. 猛击我 [下载](https://github.com/viko16/navodhtml5/raw/master/navodhtml5.crx)\r\n1. 打开「扩展程序」页面\r\n1. 勾选「开发者模式」\r\n1. 将下载好的 `.crx` 文件拖到进去\r\n1. 搞掂！\r\n\r\n\r\n作用\r\n==============\r\n1. 用「HTML5播放器」替换了官方的「Flash播放器」\r\n1. 方便「视频下载」\r\n1. 增加了「音量记忆」功能（官方的没有提供）\r\n1. 完善了「播放列表」的记录功能\r\n\r\n\r\n搞这货干嘛？\r\n==============\r\n- 为推广和普及华软 HTML5 而努力\r\n- 看着原来那只 Flash播放器 不爽啊，各种迟钝，各种卡拖动 _ (:3」∠)_\r\n- 顺便也改了官方的各种 bug 了2333....\r\n\r\n\r\n注意\r\n==============\r\n1. 此扩展只作用于 [`NA新版在线电影网`](http://navod.scse.com.cn)(内测中) 的播放页面\r\n1. 既然是 HTML5 播放器，那你应该知道`右键可以直接下载视频`了吧？~ ~","google":"","note":"Don't delete this file! It's used internally to help with page regeneration."}